pytorchjeeves/__init__.py
pytorchjeeves-0.2.0.dist-info/entry_points.txt
pytorchjeeves-0.2.0.dist-info/WHEEL
pytorchjeeves-0.2.0.dist-info/METADATA
pytorchjeeves-0.2.0.dist-info/RECORD
