Metadata-Version: 2.1
Name: pytorchjeeves
Version: 0.2.0
Summary: Utilities to help train models with pytorch
Home-page: https://github.com/soumendra/pytorchjeeves
License: MIT
Author: Soumendra Dhanee
Author-email: soumendra@gmail.com
Maintainer: Soumendra Dhanee
Maintainer-email: soumendra@gmail.com
Requires-Python: >=3.7.5,<4.0.0
Classifier: License :: OSI Approved :: MIT License
Classifier: Programming Language :: Python :: 3
Classifier: Programming Language :: Python :: 3.8
Requires-Dist: attrdict (>=2.0.1,<3.0.0)
Requires-Dist: boto (>=2.49.0,<3.0.0)
Requires-Dist: boto3 (>=1.10.44,<2.0.0)
Requires-Dist: cifar2png (>=0.0.4,<0.0.5)
Requires-Dist: click (>=7.0,<8.0)
Requires-Dist: hyperdash (>=0.15.3,<0.16.0)
Requires-Dist: loguru (>=0.4.0,<0.5.0)
Requires-Dist: opencv-python (>=4.1.2,<5.0.0)
Requires-Dist: pandas (>=0.25.3,<0.26.0)
Requires-Dist: pillow (>=6.2.1,<7.0.0)
Requires-Dist: py3nvml (>=0.2.5,<0.3.0)
Requires-Dist: scikit-image (>=0.16.2,<0.17.0)
Requires-Dist: scikit-learn (>=0.22.1,<0.23.0)
Requires-Dist: seaborn (>=0.9.0,<0.10.0)
Requires-Dist: split_folders (>=0.3.1,<0.4.0)
Requires-Dist: streamlit (>=0.53.0,<0.54.0)
Requires-Dist: torch (>=1.3.1,<2.0.0)
Requires-Dist: torchvision (>=0.4.2,<0.5.0)
Requires-Dist: tqdm (>=4.41.1,<5.0.0)
Project-URL: Documentation, https://github.com/soumendra/pytorchjeeves
Project-URL: Repository, https://github.com/soumendra/pytorchjeeves
